{
	"linklogos": "https://telegra.ph/file/9183d10f0d286969af095.jpg",
	"imgnazista": "https://telegra.ph/file/fb2762032047db19d206b.jpg",
	"imggay": "https://telegra.ph/file/514a5743857e2b6a5f9f8.jpg",
	"imgcorno": "https://telegra.ph/file/d2e7cae092c2be0815f61.jpg",
	"imggostosa": "https://telegra.ph/file/05da0c4bbdc3ddf4387db.jpg",
	"imggostoso": "https://telegra.ph/file/73a847631cfcdd3fe65b3.jpg",
	"imgfeio": "https://telegra.ph/file/bd22339646fe7f163f89c.jpg",
	"imggado": "https://telegra.ph/file/6ac2858647969cca031fd.jpg",
	"imgvesgo": "https://telegra.ph/file/2c6675f5bc489c219fbb0.jpg",
	"imgbebado": "https://telegra.ph/file/b69ac603e275e610d2c34.jpg",
	"tapacmd": "https://telegra.ph/file/841664f31eb7539c35a2d.mp4",
	"matarcmd": "https://telegra.ph/file/1135a19fceefa7074caf8.mp4",
	"beijocmd": "https://telegra.ph/file/5abd9a0dfa0034785d639.mp4",
	"chutecmd": "https://telegra.ph/file/aeabfac65d7e7217528b1.mp4",
	"fundo2": "https://telegra.ph/file/9183d10f0d286969af095.jpg",
	"fundo1": "https://telegra.ph/file/49257e72a5dc0b1af1f99.jpg",
	"cdd": "480000",
	"crtt": "ğ‰ğğ†ğ ğƒğ€ ğ•ğ„ğ‹ğ‡ğ€",
	"forwarding": false,
	"banChats": false,
	"dono1": ".",
	"dono2": ".",
	"dono3": ".",
	"dono4": ".",
	"dono5": ".",
	"dono6": "."
}